PyGameAutoAndroid/PyGameAutoAndroid.py
PyGameAutoAndroid/__init__.py
xiaopy/__init__.py
xiaopy/xiaopy.py
xiaopy-0.0.21.dist-info/METADATA
xiaopy-0.0.21.dist-info/WHEEL
xiaopy-0.0.21.dist-info/top_level.txt
xiaopy-0.0.21.dist-info/RECORD
